transfusion/__init__.py
transfusion/config.py
transfusion/dataset.py
transfusion/diffusion.py
transfusion/eval.py
transfusion/model.py
transfusion/score.py
transfusion/utils.py
transfusion/wavlm_modules.py
wavlm/WavLM.py
wavlm/__init__.py
wavlm/extract.py
wavlm/modules.py
transfusion_asr-0.1.0.dist-info/LICENSE
transfusion_asr-0.1.0.dist-info/METADATA
transfusion_asr-0.1.0.dist-info/WHEEL
transfusion_asr-0.1.0.dist-info/top_level.txt
transfusion_asr-0.1.0.dist-info/RECORD
