Metadata-Version: 2.1
Name: transfusion-asr
Version: 0.1.0
Summary: TransFusion: Transcribing Speech with Multinomial Diffusion
License-File: LICENSE
